<?xml version="1.0" encoding="utf-8" ?>
<dwsync>
<file name="ionic.scss" server="ftp.smarterasp.net" local="131260471489605074" remote="131260897200000000" Dst="2" />
<file name="tsconfig.json" server="ftp.smarterasp.net" local="131260471489990066" remote="131260897200000000" Dst="2" />
<file name="_action-sheet.scss" server="ftp.smarterasp.net" local="131260471490005072" remote="131260897200000000" Dst="2" />
<file name="_animations.scss" server="ftp.smarterasp.net" local="131260471490015063" remote="131260897200000000" Dst="2" />
<file name="_backdrop.scss" server="ftp.smarterasp.net" local="131260471490025083" remote="131260897200000000" Dst="2" />
<file name="_badge.scss" server="ftp.smarterasp.net" local="131260471490035063" remote="131260897200000000" Dst="2" />
<file name="_bar.scss" server="ftp.smarterasp.net" local="131260471490055085" remote="131260897200000000" Dst="2" />
<file name="_button-bar.scss" server="ftp.smarterasp.net" local="131260471490065069" remote="131260897200000000" Dst="2" />
<file name="_button.scss" server="ftp.smarterasp.net" local="131260471490080061" remote="131260897200000000" Dst="2" />
<file name="_checkbox.scss" server="ftp.smarterasp.net" local="131260471490100068" remote="131260897800000000" Dst="2" />
<file name="_form.scss" server="ftp.smarterasp.net" local="131260471490115067" remote="131260897800000000" Dst="2" />
<file name="_grid.scss" server="ftp.smarterasp.net" local="131260471490125066" remote="131260897800000000" Dst="2" />
<file name="_list.scss" server="ftp.smarterasp.net" local="131260471490225070" remote="131260897800000000" Dst="2" />
<file name="_items.scss" server="ftp.smarterasp.net" local="131260471490210201" remote="131260897800000000" Dst="2" />
<file name="_loading.scss" server="ftp.smarterasp.net" local="131260471490235075" remote="131260897800000000" Dst="2" />
<file name="_menu.scss" server="ftp.smarterasp.net" local="131260471490250060" remote="131260897800000000" Dst="2" />
<file name="_mixins.scss" server="ftp.smarterasp.net" local="131260471490265070" remote="131260897800000000" Dst="2" />
<file name="_modal.scss" server="ftp.smarterasp.net" local="131260471490280069" remote="131260897800000000" Dst="2" />
<file name="_platform.scss" server="ftp.smarterasp.net" local="131260471490290071" remote="131260897800000000" Dst="2" />
<file name="_popover.scss" server="ftp.smarterasp.net" local="131260471490300073" remote="131260897800000000" Dst="2" />
<file name="_popup.scss" server="ftp.smarterasp.net" local="131260471490310064" remote="131260897800000000" Dst="2" />
<file name="_progress.scss" server="ftp.smarterasp.net" local="131260471490320073" remote="131260897800000000" Dst="2" />
<file name="_radio.scss" server="ftp.smarterasp.net" local="131260471490330067" remote="131260897800000000" Dst="2" />
<file name="_refresher.scss" server="ftp.smarterasp.net" local="131260471490355072" remote="131260897800000000" Dst="2" />
<file name="_range.scss" server="ftp.smarterasp.net" local="131260471490345067" remote="131260897800000000" Dst="2" />
<file name="_reset.scss" server="ftp.smarterasp.net" local="131260471490375065" remote="131260897800000000" Dst="2" />
<file name="_scaffolding.scss" server="ftp.smarterasp.net" local="131260471490390156" remote="131260897800000000" Dst="2" />
<file name="_select.scss" server="ftp.smarterasp.net" local="131260471490405070" remote="131260897800000000" Dst="2" />
<file name="_slide-box.scss" server="ftp.smarterasp.net" local="131260471490535066" remote="131260897800000000" Dst="2" />
<file name="_slides.scss" server="ftp.smarterasp.net" local="131260471490555069" remote="131260897800000000" Dst="2" />
<file name="_spinner.scss" server="ftp.smarterasp.net" local="131260471490570068" remote="131260897800000000" Dst="2" />
<file name="_tabs.scss" server="ftp.smarterasp.net" local="131260471490665079" remote="131260897800000000" Dst="2" />
<file name="_toggle.scss" server="ftp.smarterasp.net" local="131260471490685082" remote="131260897800000000" Dst="2" />
<file name="_transitions.scss" server="ftp.smarterasp.net" local="131260471490700074" remote="131260897800000000" Dst="2" />
<file name="_type.scss" server="ftp.smarterasp.net" local="131260471490710076" remote="131260897800000000" Dst="2" />
<file name="_util.scss" server="ftp.smarterasp.net" local="131260471490730076" remote="131260897800000000" Dst="2" />
<file name="_variables.scss" server="ftp.smarterasp.net" local="131260471490805069" remote="131260897800000000" Dst="2" />
</dwsync>